p2w4n/__init__.py
p2w4n/__main__.py
p2w4n/pdf2word.py
p2w4n/pptx2word.py
p2w4n/word.py
p2w4n-1.4.0.dist-info/METADATA
p2w4n-1.4.0.dist-info/WHEEL
p2w4n-1.4.0.dist-info/entry_points.txt
p2w4n-1.4.0.dist-info/top_level.txt
p2w4n-1.4.0.dist-info/RECORD
