Metadata-Version: 2.1
Name: p2w4n
Version: 1.4.0
Summary: Convert PDF/PPT(X) file word document readfy for import into Notion.
Home-page: https://www.3thinking.cn/p2w4n/
Author: Learner Chen
Author-email: learner.chen@icloud.com
License: NO-DISTRIBUTION
Platform: UNKNOWN
Classifier: Programming Language :: Python
Classifier: Programming Language :: Python :: 3.7
Requires-Dist: PyMuPDF (==1.20.2)
Requires-Dist: pywin32 (==304)
